claude_dash/__init__.py
claude_dash/__main__.py
claude_dash/__version__.py
claude_dash/main.py
claude_dash/config/defaults/config.json
claude_dash/config/defaults/pricing.json
claude_dash/core/__init__.py
claude_dash/core/config_loader.py
claude_dash/core/data_analyzer.py
claude_dash/core/default_config.py
claude_dash/core/paths.py
claude_dash/providers/__init__.py
claude_dash/providers/base.py
claude_dash/providers/claude_code_reader.py
claude_dash/ui/__init__.py
claude_dash/ui/layout_manager.py
claude_dash/ui/theme_manager.py
claude_dash/ui/cards/__init__.py
claude_dash/ui/cards/base_card.py
claude_dash/ui/cards/claude_code_card.py
claude_dash/ui/cards/pacman_card.py
claude_dash/ui/cards/simple_card.py
claude_dash/ui/cards/theme_selector_card.py
claude_dash/ui/cards/value_analysis_card.py
claude_dash-0.9.2.dist-info/licenses/LICENSE
claude_dash-0.9.2.dist-info/METADATA
claude_dash-0.9.2.dist-info/WHEEL
claude_dash-0.9.2.dist-info/entry_points.txt
claude_dash-0.9.2.dist-info/top_level.txt
claude_dash-0.9.2.dist-info/RECORD
