Metadata-Version: 2.4
Name: claude-dash
Version: 0.9.2
Summary: Monitor your Claude usage and subscription value
Author-email: Michael Coen <mhcoen@gmail.com>
License: Apache-2.0
Project-URL: Homepage, https://github.com/mhcoen/claude-dash
Project-URL: Repository, https://github.com/mhcoen/claude-dash
Project-URL: Issues, https://github.com/mhcoen/claude-dash/issues
Keywords: claude,monitoring,usage,analytics,dashboard
Classifier: Development Status :: 4 - Beta
Classifier: Intended Audience :: Developers
Classifier: License :: OSI Approved :: Apache Software License
Classifier: Programming Language :: Python :: 3
Classifier: Programming Language :: Python :: 3.8
Classifier: Programming Language :: Python :: 3.9
Classifier: Programming Language :: Python :: 3.10
Classifier: Programming Language :: Python :: 3.11
Classifier: Programming Language :: Python :: 3.12
Classifier: Topic :: Software Development :: Libraries :: Python Modules
Classifier: Topic :: System :: Monitoring
Requires-Python: >=3.8
License-File: LICENSE
Requires-Dist: PyQt6>=6.0.0
Requires-Dist: python-dateutil>=2.8.0
Dynamic: license-file
